kucoin/__init__.py
kucoin/client.py
kucoin/ws_client.py
kucoin/base_request/__init__.py
kucoin/base_request/base_request.py
kucoin/earn/__init__.py
kucoin/earn/earn.py
kucoin/lending/__init__.py
kucoin/lending/lending.py
kucoin/margin/__init__.py
kucoin/margin/margin.py
kucoin/market/__init__.py
kucoin/market/market.py
kucoin/trade/__init__.py
kucoin/trade/trade.py
kucoin/user/__init__.py
kucoin/user/user.py
kucoin/websocket/__init__.py
kucoin/websocket/websocket.py
kucoin/ws_token/__init__.py
kucoin/ws_token/token.py
kucoin_python-1.0.25.dist-info/LICENSE
kucoin_python-1.0.25.dist-info/METADATA
kucoin_python-1.0.25.dist-info/WHEEL
kucoin_python-1.0.25.dist-info/top_level.txt
kucoin_python-1.0.25.dist-info/RECORD
